busie_consumer/__init__.py
busie_consumer/helpers.py
tests/__init__.py
tests/conftest.py
tests/test_busie_consumer.py
busie_consumer-1.0.0.dist-info/METADATA
busie_consumer-1.0.0.dist-info/WHEEL
busie_consumer-1.0.0.dist-info/top_level.txt
busie_consumer-1.0.0.dist-info/RECORD
