Metadata-Version: 2.1
Name: busie-consumer
Version: 1.0.0
Summary: Base Kafka Consumer for Busie Projects
Home-page: https://bradyperry@bitbucket.org/busie/busie-consumer.git
Author: Brady Perry
Author-email: brady@getbusie.com
License: UNKNOWN
Platform: UNKNOWN
Classifier: Programming Language :: Python :: 3
Classifier: License :: OSI Approved :: MIT License
Classifier: Operating System :: OS Independent
Requires-Python: >=3.6
Requires-Dist: confluent-kafka
